Metadata-Version: 1.1
Name: pyarchey2
Version: 2.0.2
Summary: PyArchey2 is a fork of PyArchey. It is an attempt to speed up PyArchey by introducing multithreading and dropping support for Python2.
Home-page: https://github.com/renyi/pyarchey2
Author: Renyi Khor
Author-email: renyi.ace@gmail.com
License: GPL
Keywords: system info,ascii art,archey
Platform: UNKNOWN
Classifier: Development Status :: 4 - Beta
Classifier: License :: OSI Approved :: GNU General Public License v3 or later (GPLv3+)
Classifier: Programming Language :: Python :: 3.6
Classifier: Programming Language :: Python :: 3.7
Classifier: Operating System :: Unix
Classifier: Operating System :: MacOS :: MacOS X
Classifier: Operating System :: POSIX
Classifier: Topic :: Utilities
Classifier: Topic :: System :: Shells
Classifier: Environment :: Console
